pypacker/__init__.py
pypacker/checksum.py
pypacker/interceptor.py
pypacker/lazydict.py
pypacker/oui_stripped.txt
pypacker/pcapng.py
pypacker/ppcap.py
pypacker/psocket.py
pypacker/pypacker.py
pypacker/pypacker_meta.py
pypacker/statemachine.py
pypacker/structcbs.py
pypacker/triggerlist.py
pypacker/tuntap.py
pypacker/utils.py
pypacker/layer12/__init__.py
pypacker/layer12/aoe.py
pypacker/layer12/arp.py
pypacker/layer12/btle.py
pypacker/layer12/can.py
pypacker/layer12/dtp.py
pypacker/layer12/ethernet.py
pypacker/layer12/flow_control.py
pypacker/layer12/ieee80211.py
pypacker/layer12/lacp.py
pypacker/layer12/linuxcc.py
pypacker/layer12/llc.py
pypacker/layer12/lldp.py
pypacker/layer12/ppp.py
pypacker/layer12/pppoe.py
pypacker/layer12/prism.py
pypacker/layer12/radiotap.py
pypacker/layer12/slac.py
pypacker/layer12/stp.py
pypacker/layer12/vrrp.py
pypacker/layer3/__init__.py
pypacker/layer3/esp.py
pypacker/layer3/icmp.py
pypacker/layer3/icmp6.py
pypacker/layer3/igmp.py
pypacker/layer3/ip.py
pypacker/layer3/ip6.py
pypacker/layer3/ip_shared.py
pypacker/layer3/ipx.py
pypacker/layer3/ospf.py
pypacker/layer3/pim.py
pypacker/layer4/__init__.py
pypacker/layer4/sctp.py
pypacker/layer4/ssl.py
pypacker/layer4/ssl_ciphersuites.py
pypacker/layer4/tcp.py
pypacker/layer4/udp.py
pypacker/layer567/__init__.py
pypacker/layer567/bgp.py
pypacker/layer567/der.py
pypacker/layer567/dhcp.py
pypacker/layer567/diameter.py
pypacker/layer567/dns.py
pypacker/layer567/hsrp.py
pypacker/layer567/http.py
pypacker/layer567/iso15118.py
pypacker/layer567/mqtt.py
pypacker/layer567/ntp.py
pypacker/layer567/pmap.py
pypacker/layer567/ptpv2.py
pypacker/layer567/radius.py
pypacker/layer567/rfb.py
pypacker/layer567/rip.py
pypacker/layer567/rtp.py
pypacker/layer567/sip.py
pypacker/layer567/smb.py
pypacker/layer567/someip.py
pypacker/layer567/stun.py
pypacker/layer567/telnet.py
pypacker/layer567/tftp.py
pypacker/layer567/tpkt.py
pypacker-5.0.dist-info/AUTHORS
pypacker-5.0.dist-info/LICENSE
pypacker-5.0.dist-info/LICENSE_BSD
pypacker-5.0.dist-info/METADATA
pypacker-5.0.dist-info/WHEEL
pypacker-5.0.dist-info/top_level.txt
pypacker-5.0.dist-info/RECORD
