Metadata-Version: 2.1
Name: pypacker
Version: 5.0
Summary: Pypacker: The fast and simple packet creating and parsing module
Home-page: https://gitlab.com/mike01/pypacker
Author: Michael Stahn
Author-email: michael.stahn.42@gmail.com
License: GPLv2
Platform: UNKNOWN
Classifier: Development Status :: 6 - Mature
Classifier: Intended Audience :: Developers
Classifier: License :: OSI Approved :: GNU General Public License v2 (GPLv2)
Classifier: Natural Language :: English
Classifier: Programming Language :: Python :: 3.3
Classifier: Programming Language :: Python :: 3.4
Classifier: Programming Language :: Python :: 3.5
Classifier: Programming Language :: Python :: 3.6
Classifier: Programming Language :: Python :: Implementation :: CPython
Classifier: Programming Language :: Python :: Implementation :: PyPy
Requires-Python: >=3.3.*
